cesium_script/__init__.py
cesium_script/czml/__init__.py
cesium_script/czml/juice_offsets.py
cesium_script/czml/scene.py
cesium_script/czml/sensor.py
cesium_script/czml/util.py
cesium_script/geojson/observations.py
cesium_script/jupyter/connector.py
cesium_script/py.typed
cesium_script/quicklook_coverage.py
cesium_script/scene_generator.py
cesium_script/util/decorator.py
cesium_script/util/format.py
cesium_script/util/http.py
cesium_script/util/observation_csv.py
cesium_script-1.2.1.dist-info/METADATA
cesium_script-1.2.1.dist-info/WHEEL
cesium_script-1.2.1.dist-info/entry_points.txt
cesium_script-1.2.1.dist-info/RECORD
