Metadata-Version: 2.1
Name: cesium-script
Version: 1.2.1
Summary: Collection of scripts and utils to generate inputs for a Cesium based JUICE SOC application
Home-page: https://.github.io/cesium-script
License: MIT
Author: Rafael Andres
Author-email: rafael.andres@ext.esa.int
Requires-Python: >=3.9,<3.12
Classifier: Development Status :: 4 - Beta
Classifier: Intended Audience :: Developers
Classifier: License :: OSI Approved :: MIT License
Classifier: Operating System :: OS Independent
Classifier: Programming Language :: Python
Classifier: Programming Language :: Python :: 3
Classifier: Programming Language :: Python :: 3.9
Classifier: Programming Language :: Python :: 3.10
Classifier: Programming Language :: Python :: 3.11
Classifier: Topic :: Software Development :: Libraries :: Python Modules
Classifier: Typing :: Typed
Requires-Dist: czml3 (>=0.7.0,<0.8.0)
Requires-Dist: geojson (>=3.0.1,<4.0.0)
Requires-Dist: planetary-coverage (==1.1.0)
Requires-Dist: requests (>=2.31.0,<3.0.0)
Requires-Dist: shapely (>=2.0.1,<3.0.0)
Requires-Dist: spiceypy (>=5.1.2,<6.0.0)
Project-URL: Documentation, https://.github.io/cesium-script
Project-URL: Repository, https://github.com//cesium-script
